MANIFEST.in
README.md
pyproject.toml
setup.py
src/libmem/__init__.py
src/libmem.egg-info/PKG-INFO
src/libmem.egg-info/SOURCES.txt
src/libmem.egg-info/dependency_links.txt
src/libmem.egg-info/top_level.txt
src/libmem/_libmem/libmem-py.c
src/libmem/_libmem/types.h
tests/tests.py