Metadata-Version: 2.4
Name: libmem
Version: 5.1.4
Summary: Advanced Game Hacking Library (Windows/Linux/FreeBSD)
Home-page: https://github.com/rdbo/libmem
Author: rdbo
Project-URL: Documentation, https://github.com/rdbo/libmem/blob/master/docs/DOCS.md
Project-URL: Bug Tracker, https://github.com/rdbo/libmem/issues
Project-URL: Discord Server, https://discord.com/invite/Qw8jsPD99X
Keywords: gamehacking memory process hooking detouring hacking winapi linux freebsd
Requires-Python: >=3.6
Dynamic: author
Dynamic: description-content-type
Dynamic: home-page
Dynamic: keywords
Dynamic: project-url
Dynamic: requires-python
Dynamic: summary
